Workbook

Sheet 【データ入力】
B2: 【データ入力】 | D2: 予算： | E2: 2018年度 | G2: 実績： | H2: 2018年度
B3: ※下表の色付きセルに入力ください
B4: ●2018年度予算 | N4: 単位： 千円 | U4: 単位： 千円
C5: 1Q | F5: 2Q | I5: 3Q | L5: 4Q | O5: 1Q | P5: 2Q | Q5: 3Q | R5: 4Q | S5: 上期 | T5: 下期 | U5: 合計
C6: 4 | D6: 5 | E6: 6 | F6: 7 | G6: 8 | H6: 9 | I6: 10 | J6: 11 | K6: 12 | L6: 1 | M6: 2 | N6: 3
B7: 売上高実績 | C7: =+実績見込予算!E31 -> 483343.02 | D7: =+実績見込予算!F31 -> 506279.1 | E7: =+実績見込予算!G31 -> 497007.37 | F7: =+実績見込予算!H31 -> 520531.62 | G7: =+実績見込予算!I31 -> 514603.67 | H7: =+実績見込予算!J31 -> 524026.53 | I7: =+実績見込予算!K31 -> 525588.47 | J7: =+実績見込予算!L31 -> 529321.78 | ... N7: =+実績見込予算!P31 -> 513607.89 | O7: =SUM(C7:E7) -> 1486629.5 | P7: =SUM(F7:H7) -> 1559161.8 | Q7: =SUM(I7:K7) -> 1576212.2 | R7: =SUM(L7:N7) -> 1539159.3 | S7: =SUM(O7:P7) -> 3045791.3 | T7: =SUM(Q7:R7) -> 3115371.4 | U7: =SUM(S7:T7) -> 6161162.7
B8: 営業利益実績 | C8: =+実績見込予算!E33 -> 74732.749 | D8: =+実績見込予算!F33 -> 89548.246 | E8: =+実績見込予算!G33 -> 75910.724 | F8: =+実績見込予算!H33 -> 103820.92 | G8: =+実績見込予算!I33 -> 100143.84 | H8: =+実績見込予算!J33 -> 100964.33 | I8: =+実績見込予算!K33 -> 106665.23 | J8: =+実績見込予算!L33 -> 109866.55 | ... N8: =+実績見込予算!P33 -> 103862.5 | O8: =SUM(C8:E8) -> 240191.72 | P8: =SUM(F8:H8) -> 304929.09 | Q8: =SUM(I8:K8) -> 318300.52 | R8: =SUM(L8:N8) -> 311792.18 | S8: =SUM(O8:P8) -> 545120.81 | T8: =SUM(Q8:R8) -> 630092.7 | U8: =SUM(S8:T8) -> 1175213.5
B9: 営業利益率 | C9: =SUM(C8/C7) -> 0.15461638 | D9: =SUM(D8/D7) -> 0.17687526 | E9: =SUM(E8/E7) -> 0.15273561 | F9: =SUM(F8/F7) -> 0.1994517 | G9: =SUM(G8/G7) -> 0.19460382 | H9: =SUM(H8/H7) -> 0.19267027 | I9: =SUM(I8/I7) -> 0.20294438 | J9: =SUM(J8/J7) -> 0.20756099 | ... U9: =SUM(U8/U7) -> 0.19074541
B12: ●2018年度実・見込 | N12: 単位： 千円 | U12: 単位： 千円
C13: 1Q | F13: 2Q | I13: 3Q | L13: 4Q | O13: 1Q | P13: 2Q | Q13: 3Q | R13: 4Q | S13: 上期 | T13: 下期 | U13: 合計
C14: 4 | D14: 5 | E14: 6 | F14: 7 | G14: 8 | H14: 9 | I14: 10 | J14: 11 | K14: 12 | L14: 1 | M14: 2 | N14: 3
B15: 売上高予算 | C15: =+実績見込予算!E32 -> 499841.72 | D15: =+実績見込予算!F32 -> 504945.39 | E15: =+実績見込予算!G32 -> 507247.43 | F15: =+実績見込予算!H32 -> 555489.46 | G15: =+実績見込予算!I32 -> 548441.69 | H15: =+実績見込予算!J32 -> 582096.89 | I15: =+実績見込予算!K32 -> 619845.7 | J15: =+実績見込予算!L32 -> 622891.62 | ... N15: =+実績見込予算!P32 -> 592948.2 | O15: =SUM(C15:E15) -> 1512034.5 | P15: =SUM(F15:H15) -> 1686028 | Q15: =SUM(I15:K15) -> 1860845.4 | R15: =SUM(L15:N15) -> 1781406.2 | S15: =SUM(O15:P15) -> 3198062.6 | T15: =SUM(Q15:R15) -> 3642251.6 | U15: =SUM(S15:T15) -> 6840314.2
B16: 営業利益予算 | C16: =+実績見込予算!E34 -> 75435.085 | D16: =+実績見込予算!F34 -> 78912.892 | E16: =+実績見込予算!G34 -> 85485.532 | F16: =+実績見込予算!H34 -> 99301.796 | G16: =+実績見込予算!I34 -> 101020.88 | H16: =+実績見込予算!J34 -> 100859.21 | I16: =+実績見込予算!K34 -> 128299.75 | J16: =+実績見込予算!L34 -> 126624.21 | ... N16: =+実績見込予算!P34 -> 121819.01 | O16: =SUM(C16:E16) -> 239833.51 | P16: =SUM(F16:H16) -> 301181.88 | Q16: =SUM(I16:K16) -> 379863.37 | R16: =SUM(L16:N16) -> 356569.04 | S16: =SUM(O16:P16) -> 541015.39 | T16: =SUM(Q16:R16) -> 736432.41 | U16: =SUM(S16:T16) -> 1277447.8
B17: 営業利益率（予算） | C17: =SUM(C16/C15) -> 0.15091794 | D17: =SUM(D16/D15) -> 0.15628005 | E17: =SUM(E16/E15) -> 0.16852827 | F17: =SUM(F16/F15) -> 0.1787645 | G17: =SUM(G16/G15) -> 0.18419621 | H17: =SUM(H16/H15) -> 0.17326877 | I17: =SUM(I16/I15) -> 0.20698659 | J17: =SUM(J16/J15) -> 0.20328449 | ... U17: =SUM(U16/U15) -> 0.1867528
B19: ↓上記グラフからの自動リンク / 発表書式への自動リンク
B20: 【グラフ用（自動入力）】
B22: =B4 -> ●2018年度予算 | C22: 予算 | U22: 単位： 百万円
C23: 1Q | F23: 2Q | I23: 3Q | L23: 4Q | O23: 1Q | P23: 2Q | Q23: 3Q | R23: 4Q | S23: 上期 | T23: 下期 | U23: 合計
C24: 4 | D24: 5 | E24: 6 | F24: 7 | G24: 8 | H24: 9 | I24: 10 | J24: 11 | K24: 12 | L24: 1 | M24: 2 | N24: 3
B25: =B7 -> 売上高実績 | C25: =C7/1000 -> 483.34302 | D25: =D7/1000 -> 506.2791 | E25: =E7/1000 -> 497.00737 | F25: =F7/1000 -> 520.53162 | G25: =G7/1000 -> 514.60367 | H25: =H7/1000 -> 524.02653 | I25: =I7/1000 -> 525.58847 | J25: =J7/1000 -> 529.32178 | ... N25: =N7/1000 -> 513.60789 | O25: =SUM(C25:E25) -> 1486.6295 | P25: =SUM(F25:H25) -> 1559.1618 | Q25: =SUM(I25:K25) -> 1576.2122 | R25: =SUM(L25:N25) -> 1539.1593 | S25: =SUM(O25:P25) -> 3045.7913 | T25: =SUM(Q25:R25) -> 3115.3714 | U25: =SUM(S25:T25) -> 6161.1627
B26: =B8 -> 営業利益実績 | C26: =C8/1000 -> 74.732749 | D26: =D8/1000 -> 89.548246 | E26: =E8/1000 -> 75.910724 | F26: =F8/1000 -> 103.82092 | G26: =G8/1000 -> 100.14384 | H26: =H8/1000 -> 100.96433 | I26: =I8/1000 -> 106.66523 | J26: =J8/1000 -> 109.86655 | ... N26: =N8/1000 -> 103.8625 | O26: =SUM(C26:E26) -> 240.19172 | P26: =SUM(F26:H26) -> 304.92909 | Q26: =SUM(I26:K26) -> 318.30052 | R26: =SUM(L26:N26) -> 311.79218 | S26: =SUM(O26:P26) -> 545.12081 | T26: =SUM(Q26:R26) -> 630.0927 | U26: =SUM(S26:T26) -> 1175.2135
B27: =B9 -> 営業利益率 | C27: =C26/C25 -> 0.15461638 | D27: =D26/D25 -> 0.17687526 | E27: =E26/E25 -> 0.15273561 | F27: =F26/F25 -> 0.1994517 | G27: =G26/G25 -> 0.19460382 | H27: =H26/H25 -> 0.19267027 | I27: =I26/I25 -> 0.20294438 | J27: =J26/J25 -> 0.20756099 | ... N27: =N26/N25 -> 0.2022214 | O27: =+O26/O25 -> 0.16156798 | P27: =+P26/P25 -> 0.19557245 | Q27: =+Q26/Q25 -> 0.20194015 | R27: =+R26/R25 -> 0.20257304 | S27: =+S26/S25 -> 0.1789751 | T27: =+T26/T25 -> 0.20225283 | U27: =+U26/U25 -> 0.19074541
B30: =B12 -> ●2018年度実・見込 | C30: 実・見込 | U30: 単位： 百万円
C31: 1Q | F31: 2Q | I31: 3Q | L31: 4Q | O31: 1Q | P31: 2Q | Q31: 3Q | R31: 4Q | S31: 上期 | T31: 下期 | U31: 合計
C32: 4 | D32: 5 | E32: 6 | F32: 7 | G32: 8 | H32: 9 | I32: 10 | J32: 11 | K32: 12 | L32: 1 | M32: 2 | N32: 3
B33: =B15 -> 売上高予算 | C33: =C15/1000 -> 499.84172 | D33: =D15/1000 -> 504.94539 | E33: =E15/1000 -> 507.24743 | F33: =F15/1000 -> 555.48946 | G33: =G15/1000 -> 548.44169 | H33: =H15/1000 -> 582.09689 | I33: =I15/1000 -> 619.8457 | J33: =J15/1000 -> 622.89162 | ... N33: =N15/1000 -> 592.9482 | O33: =SUM(C33:E33) -> 1512.0345 | P33: =SUM(F33:H33) -> 1686.028 | Q33: =SUM(I33:K33) -> 1860.8454 | R33: =SUM(L33:N33) -> 1781.4062 | S33: =SUM(O33:P33) -> 3198.0626 | T33: =SUM(Q33:R33) -> 3642.2516 | U33: =SUM(S33:T33) -> 6840.3142
B34: =B16 -> 営業利益予算 | C34: =C16/1000 -> 75.435085 | D34: =D16/1000 -> 78.912892 | E34: =E16/1000 -> 85.485532 | F34: =F16/1000 -> 99.301796 | G34: =G16/1000 -> 101.02088 | H34: =H16/1000 -> 100.85921 | I34: =I16/1000 -> 128.29975 | J34: =J16/1000 -> 126.62421 | ... N34: =N16/1000 -> 121.81901 | O34: =SUM(C34:E34) -> 239.83351 | P34: =SUM(F34:H34) -> 301.18188 | Q34: =SUM(I34:K34) -> 379.86337 | R34: =SUM(L34:N34) -> 356.56904 | S34: =SUM(O34:P34) -> 541.01539 | T34: =SUM(Q34:R34) -> 736.43241 | U34: =SUM(S34:T34) -> 1277.4478
B35: =B17 -> 営業利益率（予算） | C35: =C34/C33 -> 0.15091794 | D35: =D34/D33 -> 0.15628005 | E35: =E34/E33 -> 0.16852827 | F35: =F34/F33 -> 0.1787645 | G35: =G34/G33 -> 0.18419621 | H35: =H34/H33 -> 0.17326877 | I35: =I34/I33 -> 0.20698659 | J35: =J34/J33 -> 0.20328449 | ... U35: =U34/U33 -> 0.1867528

Sheet 発表書式
C2: 部署名をご記載ください | P2: 実績： | Q2: =【データ入力】!H2 -> 2018年度 | U2: 予算： | V2: =【データ入力】!E2 -> 2018年度
C3: ■ 売上/利益 | AA3: 単位：百万円
Q4: 1Q | S4: 2Q | U4: 3Q | W4: 4Q | Y4: 通期 | AA4: 達成率/成長率
N5: 売上高 | O5: 2015 | P5: 実績 | Q5: =【データ入力】!O25 -> 1486.6295 | S5: =【データ入力】!P25 -> 1559.1618 | U5: =【データ入力】!Q25 -> 1576.2122 | W5: =【データ入力】!R25 -> 1539.1593 | Y5: =【データ入力】!U25 -> 6161.1627 | AA5: =【データ入力】!U25/【データ入力】!#REF! -> #REF!
O6: 2016 | P6: 予算 | Q6: =【データ入力】!O33 -> 1512.0345 | S6: =【データ入力】!P33 -> 1686.028 | U6: =【データ入力】!Q33 -> 1860.8454 | W6: =【データ入力】!R33 -> 1781.4062 | Y6: =【データ入力】!U33 -> 6840.3142
P7: 前期比 | Q7: =Q6/Q5 -> 1.017089 | S7: =SUM(【データ入力】!F33:H33) -> 1686.028 | U7: =SUM(【データ入力】!I33:K33) -> 1860.8454 | W7: =SUM(【データ入力】!L33:N33) -> 1781.4062 | Y7: =【データ入力】!U33 -> 6840.3142
N8: 営業利益 | O8: 2015 | P8: 実績 | Q8: =【データ入力】!O26 -> 240.19172 | S8: =【データ入力】!P26 -> 304.92909 | U8: =【データ入力】!Q26 -> 318.30052 | W8: =【データ入力】!R26 -> 311.79218 | Y8: =【データ入力】!U26 -> 1175.2135 | AA8: =【データ入力】!U26/【データ入力】!#REF! -> #REF!
O9: 2016 | P9: 予算 | Q9: =【データ入力】!O34 -> 239.83351 | S9: =【データ入力】!P34 -> 301.18188 | U9: =【データ入力】!Q34 -> 379.86337 | W9: =【データ入力】!R34 -> 356.56904 | Y9: =【データ入力】!U34 -> 1277.4478
P10: 前期比 | Q10: =Q9/Q8 -> 0.99850865 | S10: =S9/S8 -> 0.98771122 | U10: =U9/U8 -> 1.1934111 | W10: =W9/W8 -> 1.1436113 | Y10: =Y9/Y8 -> 1.0869921
N11: 営業 利益率 | O11: 2015 | P11: 実績 | Q11: =Q8/Q5 -> 0.16156798 | S11: =S8/S5 -> 0.19557245 | U11: =U8/U5 -> 0.20194015 | W11: =W8/W5 -> 0.20257304 | Y11: =Y8/Y5 -> 0.19074541
O12: 2016 | P12: 予算 | Q12: =Q9/Q6 -> 0.15861642 | S12: =S9/S6 -> 0.17863397 | U12: =U9/U6 -> 0.20413483 | W12: =W9/W6 -> 0.20016156 | Y12: =Y9/Y6 -> 0.1867528
N14: ■在庫（実績/目標） | S14: （百万円） | U14: ■設備投資（予算） | AA14: （百万円）
N15: 原材料 | P15: 期首 | R15: 期末 | U15: 増産対応
N16: 貯蔵品 仕掛品 | P16: 16年3月末 | R16: 17年3月末 | U16: 生産性向上
N17: 完成品 商品 | U17: 品質改善
N18: 金額 | U18: その他
N19: 在庫日数 | U19: 合計 | Y19: =SUM(Y15:AB18) -> 0
C21: ■ | D21: =【データ入力】!H2 -> 2018年度 | H21: 結果 | P21: ■ | Q21: =【データ入力】!E2 -> 2018年度 | U21: 施策

Sheet 発表書式 (2)
C2: 部署名をご記載ください | P2: 実績： | Q2: =【データ入力】!H2 -> 2018年度 | U2: 予算： | V2: =【データ入力】!E2 -> 2018年度
C3: ■ 売上/利益 | AA3: 単位：百万円
Q4: 1Q | S4: 2Q | U4: 3Q | W4: 4Q | Y4: 通期 | AA4: 達成率/成長率
N5: 売上高 | O5: 2015 | P5: 実績 | Q5: =【データ入力】!O25 -> 1486.6295 | S5: =【データ入力】!P25 -> 1559.1618 | U5: =【データ入力】!Q25 -> 1576.2122 | W5: =【データ入力】!R25 -> 1539.1593 | Y5: =【データ入力】!U25 -> 6161.1627 | AA5: =【データ入力】!U25/【データ入力】!#REF! -> #REF!
O6: 2016 | P6: 予算 | Q6: =【データ入力】!O33 -> 1512.0345 | S6: =【データ入力】!P33 -> 1686.028 | U6: =【データ入力】!Q33 -> 1860.8454 | W6: =【データ入力】!R33 -> 1781.4062 | Y6: =【データ入力】!U33 -> 6840.3142
P7: 前期比 | Q7: =Q6/Q5 -> 1.017089 | S7: =SUM(【データ入力】!F33:H33) -> 1686.028 | U7: =SUM(【データ入力】!I33:K33) -> 1860.8454 | W7: =SUM(【データ入力】!L33:N33) -> 1781.4062 | Y7: =【データ入力】!U33 -> 6840.3142
N8: 営業利益 | O8: 2015 | P8: 実績 | Q8: =【データ入力】!O26 -> 240.19172 | S8: =【データ入力】!P26 -> 304.92909 | U8: =【データ入力】!Q26 -> 318.30052 | W8: =【データ入力】!R26 -> 311.79218 | Y8: =【データ入力】!U26 -> 1175.2135 | AA8: =【データ入力】!U26/【データ入力】!#REF! -> #REF!
O9: 2016 | P9: 予算 | Q9: =【データ入力】!O34 -> 239.83351 | S9: =【データ入力】!P34 -> 301.18188 | U9: =【データ入力】!Q34 -> 379.86337 | W9: =【データ入力】!R34 -> 356.56904 | Y9: =【データ入力】!U34 -> 1277.4478
P10: 前期比 | Q10: =Q9/Q8 -> 0.99850865 | S10: =S9/S8 -> 0.98771122 | U10: =U9/U8 -> 1.1934111 | W10: =W9/W8 -> 1.1436113 | Y10: =Y9/Y8 -> 1.0869921
N11: 営業 利益率 | O11: 2015 | P11: 実績 | Q11: =Q8/Q5 -> 0.16156798 | S11: =S8/S5 -> 0.19557245 | U11: =U8/U5 -> 0.20194015 | W11: =W8/W5 -> 0.20257304 | Y11: =Y8/Y5 -> 0.19074541
O12: 2016 | P12: 予算 | Q12: =Q9/Q6 -> 0.15861642 | S12: =S9/S6 -> 0.17863397 | U12: =U9/U6 -> 0.20413483 | W12: =W9/W6 -> 0.20016156 | Y12: =Y9/Y6 -> 0.1867528
C14: ■ | D14: =【データ入力】!H2 -> 2018年度 | H14: 結果 | P14: ■ | Q14: =【データ入力】!E2 -> 2018年度 | U14: 施策

Sheet 発表書式 (3)
C2: 部署名をご記載ください | P2: 実績： | Q2: =【データ入力】!H2 -> 2018年度 | U2: 予算： | V2: =【データ入力】!E2 -> 2018年度
C3: ■ 売上/利益 | AA3: 単位：百万円
Q4: 1Q | S4: 2Q | U4: 3Q | W4: 4Q | Y4: 通期 | AA4: 達成率/成長率
N5: 売上高 | O5: 2015 | P5: 実績 | Q5: =【データ入力】!O25 -> 1486.6295 | S5: =【データ入力】!P25 -> 1559.1618 | U5: =【データ入力】!Q25 -> 1576.2122 | W5: =【データ入力】!R25 -> 1539.1593 | Y5: =【データ入力】!U25 -> 6161.1627 | AA5: =【データ入力】!U25/【データ入力】!#REF! -> #REF!
O6: 2016 | P6: 予算 | Q6: =【データ入力】!O33 -> 1512.0345 | S6: =【データ入力】!P33 -> 1686.028 | U6: =【データ入力】!Q33 -> 1860.8454 | W6: =【データ入力】!R33 -> 1781.4062 | Y6: =【データ入力】!U33 -> 6840.3142
P7: 前期比 | Q7: =Q6/Q5 -> 1.017089 | S7: =S6/S5 -> 1.0813682 | U7: =U6/U5 -> 1.1805805 | W7: =W6/W5 -> 1.1573891 | Y7: =Y6/Y5 -> 1.1102311
N8: 営業利益 | O8: 2015 | P8: 実績 | Q8: =【データ入力】!O26 -> 240.19172 | S8: =【データ入力】!P26 -> 304.92909 | U8: =【データ入力】!Q26 -> 318.30052 | W8: =【データ入力】!R26 -> 311.79218 | Y8: =【データ入力】!U26 -> 1175.2135 | AA8: =【データ入力】!U26/【データ入力】!#REF! -> #REF!
O9: 2016 | P9: 予算 | Q9: =【データ入力】!O34 -> 239.83351 | S9: =【データ入力】!P34 -> 301.18188 | U9: =【データ入力】!Q34 -> 379.86337 | W9: =【データ入力】!R34 -> 356.56904 | Y9: =【データ入力】!U34 -> 1277.4478
P10: 前期比 | Q10: =Q9/Q8 -> 0.99850865 | S10: =S9/S8 -> 0.98771122 | U10: =U9/U8 -> 1.1934111 | W10: =W9/W8 -> 1.1436113 | Y10: =Y9/Y8 -> 1.0869921
N11: 営業 利益率 | O11: 2015 | P11: 実績 | Q11: =Q8/Q5 -> 0.16156798 | S11: =S8/S5 -> 0.19557245 | U11: =U8/U5 -> 0.20194015 | W11: =W8/W5 -> 0.20257304 | Y11: =Y8/Y5 -> 0.19074541
O12: 2016 | P12: 予算 | Q12: =Q9/Q6 -> 0.15861642 | S12: =S9/S6 -> 0.17863397 | U12: =U9/U6 -> 0.20413483 | W12: =W9/W6 -> 0.20016156 | Y12: =Y9/Y6 -> 0.1867528
N14: ■在庫（実績/目標） | R14: 単位：百万円 | U14: ■設備投資（予算） | AA14: 単位：百万円
N15: 原材料 | P15: 期首 | R15: 期末 | U15: 増産対応
N16: 貯蔵品 仕掛品 | P16: 16年3月末 | R16: 17年3月末 | U16: 生産性向上
N17: 完成品 商品 | U17: 品質改善
N18: 金額 | U18: その他
N19: 在庫日数 | U19: 合計 | Y19: =SUM(Y15:AB18) -> 0
C21: ■ | D21: =【データ入力】!H2 -> 2018年度 | H21: 結果 | P21: ■ | Q21: =【データ入力】!E2 -> 2018年度 | U21: 施策

Sheet 発表資料
O1: ２０１８年９月 フォーラム 第三部発表資料
C2: MARUWA(MALAYSA) | O2: アルミナ基板事業部 | AC2: 発表者：小川
C3: ■ 売上高/営業利益 | AB3: 単位： 百万円
P4: １Q | R4: ２Q | T4: ３Q | V4: ４Q | X4: 上期 | Z4: 下期 | AB4: 通期
N5: 売上高 | O5: 予算 | P5: =【データ入力】!O25 -> 1486.6295 | R5: =【データ入力】!P25 -> 1559.1618 | T5: =【データ入力】!Q25 -> 1576.2122 | V5: =【データ入力】!R25 -> 1539.1593 | X5: =【データ入力】!S25 -> 3045.7913 | Z5: =【データ入力】!T25 -> 3115.3714 | AB5: =【データ入力】!U25 -> 6161.1627
O6: 実/見込 | P6: =【データ入力】!O33 -> 1512.0345 | R6: =【データ入力】!P33 -> 1686.028 | T6: =【データ入力】!Q33 -> 1860.8454 | V6: =【データ入力】!R33 -> 1781.4062 | X6: =【データ入力】!S33 -> 3198.0626 | Z6: =【データ入力】!T33 -> 3642.2516 | AB6: =【データ入力】!U33 -> 6840.3142
O7: 予算比 | P7: =P6/P5 -> 1.017089 | R7: =R6/R5 -> 1.0813682 | T7: =T6/T5 -> 1.1805805 | V7: =V6/V5 -> 1.1573891 | X7: =X6/X5 -> 1.049994 | Z7: =Z6/Z5 -> 1.1691227 | AB7: =AB6/AB5 -> 1.1102311
N8: 営業利益 | O8: 予算 | P8: =【データ入力】!O26 -> 240.19172 | R8: =【データ入力】!P26 -> 304.92909 | T8: =【データ入力】!Q26 -> 318.30052 | V8: =【データ入力】!R26 -> 311.79218 | X8: =【データ入力】!S26 -> 545.12081 | Z8: =【データ入力】!T26 -> 630.0927 | AB8: =【データ入力】!U26 -> 1175.2135
O9: 実/見込 | P9: =【データ入力】!O34 -> 239.83351 | R9: =【データ入力】!P34 -> 301.18188 | T9: =【データ入力】!Q34 -> 379.86337 | V9: =【データ入力】!R34 -> 356.56904 | X9: =【データ入力】!S34 -> 541.01539 | Z9: =【データ入力】!T34 -> 736.43241 | AB9: =【データ入力】!U34 -> 1277.4478
O10: 予算比 | P10: =P9/P8 -> 0.99850865 | R10: =R9/R8 -> 0.98771122 | T10: =T9/T8 -> 1.1934111 | V10: =V9/V8 -> 1.1436113 | X10: =X9/X8 -> 0.9924688 | Z10: =Z9/Z8 -> 1.1687684 | AB10: =AB9/AB8 -> 1.0869921
N11: 営業 利益率 | O11: 予算 | P11: =P8/P5 -> 0.16156798 | R11: =R8/R5 -> 0.19557245 | T11: =T8/T5 -> 0.20194015 | V11: =V8/V5 -> 0.20257304 | X11: =X8/X5 -> 0.1789751 | Z11: =Z8/Z5 -> 0.20225283 | AB11: =AB8/AB5 -> 0.19074541
O12: 実/見込 | P12: =P9/P6 -> 0.15861642 | R12: =R9/R6 -> 0.17863397 | T12: =T9/T6 -> 0.20413483 | V12: =V9/V6 -> 0.20016156 | X12: =X9/X6 -> 0.16916973 | Z12: =Z9/Z6 -> 0.20219152 | AB12: =AB9/AB6 -> 0.1867528
C14: ■ | D14: 上期結果 | P14: ■ | Q14: 下期施策
C15: ■ 収益貢献製品・商品/市場状況/競争状況 | P15: ■ 収益貢献製品・商品、ターゲット市場/懸念事項
C17: チップ抵抗・・・品不足の影響もあり売り手市場の状態 | Q17: ジルコニア基板の顧客増産対応に伴い受注確保 | Z17: 150k→250k/M
D18: 基板価格見直し 3月対比 10%値上げ | R18: （新規設備反直炉 12月末稼動予定）
D19: 競合増産 基板全体占有率 三環 50% MARUWA 15% | Q19: チップ基板価格見直し ９月対比 10%値上げ
C20: 大型基板・・・DBC用基板調整、LED用基板受注増
C21: 材料費 ８％UP、電動費 ５％UP、資材品での価格UP | Q21: 労務費（最低賃金の上昇）５％UP 2019年1月より
C23: ■ 在庫状況（18年3月末 → 18年9月末見込み） | P23: ■ 在庫削減への取組み（削減目標）
C24: 在庫回転日数 3月末 59日 → 9月末 41日 | Q24: 在庫回転日数 ２０１９年３月末 40日
C26: ■ 取組み結果（収益効果策、新製品・商品/新市場、トピックス等） | P26: ■ 収益取組み項目（見込効果、スケジュール）、収益強化策等
C27: 労務費削減 ３月末対比 １５名削減 | Q27: 外観自動検査機導入 労務費削減 20名（２０１９年1月）
C28: 歩留まり改善目標未達 SUB 目標81.0% → 80.5％ | Q28: 歩留まり改善スピードUP 技術メンバー常駐（2018年10月 2名）
C29: TPH 目標80.4％ → 73.9％(ZTA) | Q29: 顧客クレーム低減活動 2018年下期 13件（上期50％down）
C30: 顧客クレーム増加（SUB） 2018年上期 26件 （前期１４件） | Q30: 工程異常処理及び設備管理基準のルール強化

Sheet 実績見込予算
E1: 27.65
A2: アルミナ基板連結予実管理 | G2: 予算集計 | J2: 単位：千円
B3: 管理会計 | E3: 実績 | F3: 実績 | G3: 実績 | H3: 実績 | I3: 実績 | J3: 見込 | K3: 下期予算 | L3: 下期予算 | M3: 下期予算 | N3: 下期予算 | O3: 下期予算 | P3: 下期予算 | U3: 単位：千円 | X3: 単位：千円 | AB3: 単位：千円 | AC3: 単位：千円
A4: PRODUCTION PROFIT | E4: 41729 | F4: 41759 | G4: 41790 | H4: 41820 | I4: 41851 | J4: 41882 | K4: 41912 | L4: 41943 | M4: 41973 | N4: 42004 | O4: 42035 | P4: 42063 | R4: 1Q | S4: 2Q | T4: 3Q | U4: 4Q | W4: 上期 | X4: 下期 | Z4: 2015 | AA4: 2016 | AB4: 2017 | AC4: 2018 | AD4: 予算増減
A5: チップJM | C5: 外部売上 | D5: 期初予算 | E5: 0 | F5: 0 | G5: 0 | H5: 0 | I5: 0 | J5: 0 | K5: 0 | L5: 0 | M5: 0 | N5: 0 | O5: 0 | P5: 0 | R5: 0 | S5: 0 | T5: 0 | U5: 0 | W5: 0 | X5: 0 | Z5: 0 | AA5: 0 | AB5: 0 | AC5: 0
D6: 実績値 | E6: 0 | F6: 0 | G6: 0 | R6: 0 | S6: 0 | T6: 0 | U6: 0 | W6: 0 | X6: 0 | Z6: -8622.5345 | AA6: 975.138 | AB6: 300.38 | AC6: 0
C7: 営業利益 | D7: 期初予算 | E7: 0 | F7: 0 | G7: 0 | H7: 0 | I7: 0 | J7: 0 | K7: 0 | L7: 0 | M7: 0 | N7: 0 | O7: 0 | P7: 0 | R7: 0 | S7: 0 | T7: 0 | U7: 0 | W7: 0 | X7: 0 | Z7: 0 | AA7: 0 | AB7: 0 | AC7: 0
D8: 実績値 | E8: 0 | F8: 0 | G8: 0 | R8: 0 | S8: 0 | T8: 0 | U8: 0 | W8: 0 | X8: 0 | Z8: -13435.73 | AA8: 239.91642 | AB8: -955.147 | AC8: 0
A9: チップ商品+HIC | C9: 外部売上 | D9: 期初予算 | E9: 44927.775 | F9: 45091.975 | G9: 45782.775 | H9: 44991.975 | I9: 44542.055 | J9: 45511.975 | K9: 46689.18 | L9: 45686.975 | M9: 45037.055 | N9: 46476.975 | O9: 45602.055 | P9: 46476.975 | R9: 135802.52 | S9: 135046.01 | T9: 137413.21 | U9: 138556.01 | W9: 270848.53 | X9: 275969.21 | Z9: 0 | AA9: 670553.44 | AB9: 475365.6 | AC9: 546817.74
D10: 実績値 | E10: 52985.223 | F10: 43235.188 | G10: 53392.121 | H10: 56557.742 | I10: 44047.638 | J10: 45511.975 | K10: 46267.295 | L10: 46235.215 | M10: 52557.835 | N10: 49590.165 | O10: 52192.285 | P10: 52355.165 | R10: 149612.53 | S10: 146117.36 | T10: 145060.35 | U10: 154137.61 | W10: 295729.89 | X10: 299197.96 | Z10: 666844.18 | AA10: 562499.87 | AB10: 596657.66 | AC10: 594927.85
C11: 営業利益 | D11: 期初予算 | E11: -8910.0642 | F11: -8901.8542 | G11: -8867.3142 | H11: -6875 | I11: -6875 | J11: -8880.8542 | K11: -8821.994 | L11: -8872.1042 | M11: -8904.6002 | N11: -8832.6042 | O11: -8876.3502 | P11: -8832.6042 | R11: -26679.233 | S11: -22630.854 | T11: -26598.698 | U11: -26541.559 | W11: -49310.087 | X11: -53140.257 | Z11: 0 | AA11: -61004.736 | AB11: -54695.16 | AC11: -102450.34
D12: 実績値 | E12: -7736.395 | F12: -9231.928 | G12: -5002.934 | H12: -7486.984 | I12: -6827.201 | J12: -6593 | K12: -6593 | L12: -6593 | M12: -6593 | N12: -6593 | O12: -6593 | P12: -6593 | R12: -21971.257 | S12: -20907.185 | T12: -19779 | U12: -19779 | W12: -42878.442 | X12: -39558 | Z12: -91670.585 | AA12: -90297.085 | AB12: -82105.129 | AC12: -82436.442
A13: チップMM | C13: 外部売上 | D13: 期初予算 | E13: 305888.85 | F13: 307110.85 | G13: 304786.85 | H13: 324635.61 | I13: 326192.26 | J13: 323863.26 | K13: 326529.76 | L13: 332113.26 | M13: 330927.76 | N13: 315725.78 | O13: 319343.15 | P13: 318131.77 | R13: 917786.55 | S13: 974691.13 | T13: 989570.78 | U13: 953200.7 | W13: 1892477.7 | X13: 1942771.5 | Z13: 0 | AA13: 3232944.9 | AB13: 3236670.3 | AC13: 3835249.2
D14: 実績値 | E14: 293300.39 | F14: 305618.27 | G14: 289163.18 | H14: 323741.68 | I14: 334377.78 | J14: 327885.28 | K14: 340579.85 | L14: 341994.92 | M14: 339171.84 | N14: 331484.81 | O14: 324257.35 | P14: 323511.23 | R14: 888081.84 | S14: 986004.74 | T14: 1021746.6 | U14: 979253.38 | W14: 1874086.6 | X14: 2001000 | Z14: 2616865.2 | AA14: 2922223.8 | AB14: 2952301.3 | AC14: 3924464.1
C15: 内部売上 | D15: 期初予算 | E15: 41319.352 | F15: 41014.592 | G15: 41319.352 | H15: 40919.592 | I15: 41414.352 | J15: 41413.592 | K15: 42577.271 | L15: 41082.992 | M15: 41387.752 | N15: 41025.992 | O15: 41520.752 | P15: 41025.992 | R15: 123653.3 | S15: 123747.54 | T15: 125048.02 | U15: 123572.74 | Z15: 0 | AA15: 0 | AB15: 368458.19 | AC15: 496021.59
D16: 実績値 | E16: 45454.656 | F16: 46776.6 | G16: 40247.625 | H16: 36475.063 | I16: 41938.799 | J16: 41413.592 | K16: 42013.194 | L16: 42362.718 | M16: 48576.478 | N16: 45202.696 | O16: 48229.206 | P16: 47829.446 | R16: 132478.88 | S16: 119827.45 | T16: 132952.39 | U16: 141261.35 | Z16: 534952.68 | AA16: 495681.03 | AB16: 512705.14 | AC16: 526520.07
C17: 営業利益 | D17: 期初予算 | E17: 61743.929 | F17: 65333.251 | G17: 55700.489 | H17: 78838.731 | I17: 79108.432 | J17: 76457.649 | K17: 84484.595 | L17: 86544.26 | M17: 83145.116 | N17: 80952.156 | O17: 82695.113 | P17: 82147.605 | R17: 182777.67 | S17: 234404.81 | T17: 254173.97 | U17: 245794.87 | W17: 417182.48 | X17: 499968.85 | Z17: 0 | AA17: 324026.45 | AB17: 574088.07 | AC17: 917151.33
D18: 実績値 | E18: 49105.037 | F18: 53876.303 | G18: 49140.354 | H18: 59446.95 | I18: 61932.498 | J18: 52075.79 | K18: 69921.16 | L18: 66936.99 | M18: 71301.24 | N18: 69372.28 | O18: 65571.74 | P18: 70794.09 | R18: 152121.69 | S18: 173455.24 | T18: 208159.39 | U18: 205738.11 | W18: 325576.93 | X18: 413897.5 | Z18: 30230.706 | AA18: 403871.74 | AB18: 487653.73 | AC18: 728289.89
A19: チップ連結 | C19: 外部売上 | D19: 期初予算 | E19: 350816.63 | F19: 352202.83 | G19: 350569.63 | H19: 369627.59 | I19: 370734.32 | J19: 369375.24 | K19: 373218.94 | L19: 377800.24 | M19: 375964.82 | N19: 362202.76 | O19: 364945.2 | P19: 364608.75 | R19: 1053589.1 | S19: 1109737.1 | T19: 1126984 | U19: 1091756.7 | W19: 2163326.2 | X19: 2218740.7 | Z19: 0 | AA19: 3417875.8 | AB19: 3712035.9 | AC19: 4382066.9
D20: 実績値 | E20: 346285.61 | F20: 348853.45 | G20: 342555.3 | H20: 380299.43 | I20: 378425.42 | J20: 373397.25 | K20: 386847.15 | L20: 388230.13 | M20: 391729.68 | N20: 381074.97 | O20: 376449.63 | P20: 375866.4 | R20: 1037694.4 | S20: 1132122.1 | T20: 1166807 | U20: 1133391 | V20: 1.0030001 | W20: 2169816.5 | X20: 2300198 | Y20: 0.94455051 | Z20: 3275086.9 | AA20: 3485698.8 | AB20: 3549259.3 | AC20: 4519391.9
C21: 営業利益 | D21: 期初予算 | E21: 52833.864 | F21: 56431.397 | G21: 46833.175 | H21: 71963.731 | I21: 72233.432 | J21: 67576.795 | K21: 75662.601 | L21: 77672.156 | M21: 74240.516 | N21: 72119.552 | O21: 73818.763 | P21: 73315.001 | R21: 156098.44 | S21: 211773.96 | T21: 227575.27 | U21: 219253.32 | W21: 367872.39 | X21: 446828.59 | Z21: 0 | AA21: 244947.16 | AB21: 519392.91 | AC21: 814700.98
D22: 実績値 | E22: 41368.641 | F22: 44644.375 | G22: 44137.42 | H22: 51959.966 | I22: 55105.297 | J22: 45482.79 | K22: 63328.16 | L22: 60343.99 | M22: 64708.24 | N22: 62779.28 | O22: 58978.74 | P22: 64201.09 | R22: 130150.44 | S22: 152548.05 | T22: 188380.39 | U22: 185959.11 | W22: 282698.49 | X22: 374339.5 | Y22: 0.70367703 | Z22: -74875.609 | AA22: 313814.57 | AB22: 404593.46 | AC22: 645853.45
D23: 利益率 | E23: 0.11946393 | F23: 0.12797458 | G23: 0.12884757 | H23: 0.13662909 | I23: 0.14561733 | J23: 0.12180805 | K23: 0.16370331 | L23: 0.15543356 | M23: 0.16518595 | N23: 0.1647426 | O23: 0.156671 | P23: 0.17080827 | R23: 0.14815875 | S23: 0.19083254 | T23: 0.20193301 | U23: 0.20082617 | W23: 0.17004943 | X23: 0.20138838 | Z23: -0.35910326 | AA23: 1.0774259 | AB23: 0.1399213 | AC23: 1.7083194
A24: 大型基板MM | C24: 外部売上 | D24: 期初予算 | E24: 132526.39 | F24: 154076.27 | G24: 146437.74 | H24: 150904.03 | I24: 143869.36 | J24: 154651.29 | K24: 152369.53 | L24: 151521.54 | M24: 145337.11 | N24: 151090.68 | O24: 147312.76 | P24: 148999.14 | R24: 433040.4 | S24: 449424.68 | T24: 449228.17 | U24: 447402.58 | W24: 882465.08 | X24: 896630.75 | Z24: 0 | AA24: 1484951.9 | AB24: 1608163.4 | AC24: 1779095.8
D25: 実績値 | E25: 153556.11 | F25: 156091.94 | G25: 164692.13 | H25: 175190.03 | I25: 170016.27 | J25: 208699.64 | K25: 232998.55 | L25: 234661.49 | M25: 226378.39 | N25: 214249.83 | O25: 216683.6 | P25: 217081.81 | R25: 474340.18 | S25: 553905.94 | T25: 694038.44 | U25: 648015.23 | W25: 1028246.1 | X25: 1342053.7 | Z25: 1356485 | AA25: 1549762.5 | AB25: 1926616.7 | AC25: 2421897.1
C26: 内部売上 | D26: 期初予算 | E26: 1362.034 | F26: 1822.784 | G26: 2174.284 | H26: 1822.784 | I26: 900.6 | J26: 1822.784 | K26: 1777.45 | L26: 2319.634 | M26: 1397.45 | N26: 3127.134 | O26: 1801.2 | P26: 3127.134 | R26: 5359.102 | S26: 4546.168 | T26: 5494.534 | U26: 8055.468 | Z26: 0 | AA26: 0 | AB26: 8827.573 | AC26: 23455.272
D27: 実績値 | E27: 487.85739 | F27: 1040.325 | G27: 151.93778 | H27: 927.061 | I27: 2910.253 | J27: 1822.784 | K27: 2042.88 | L27: 1642.88 | M27: 1424.7 | N27: 2008.38 | O27: 1424.7 | P27: 2008.38 | R27: 1680.1202 | S27: 5660.098 | T27: 5110.46 | U27: 5441.46 | W27: 7340.2182 | X27: 10551.92 | Z27: 44009 | AA27: 32383 | AB27: 13073.06 | AC27: 17892.138
C28: 営業利益 | D28: 期初予算 | E28: 21898.885 | F28: 33116.849 | G28: 29077.549 | H28: 31857.185 | I28: 27910.409 | J28: 33387.539 | K28: 31002.626 | L28: 32194.398 | M28: 27528.228 | N28: 31981.959 | O28: 30009.397 | P28: 30547.504 | R28: 84093.282 | S28: 93155.133 | T28: 90725.251 | U28: 92538.861 | W28: 177248.41 | X28: 183264.11 | Z28: 0 | AA28: 433172.87 | AB28: 461044.87 | AC28: 360512.53
D29: 実績値 | E29: 34066.443 | F29: 34268.517 | G29: 41348.112 | H29: 47341.83 | I29: 45915.581 | J29: 55376.421 | K29: 64971.588 | L29: 66280.217 | M29: 60231.171 | N29: 55581.82 | O29: 57410.193 | P29: 57617.921 | R29: 109683.07 | S29: 148633.83 | T29: 191482.98 | U29: 170609.93 | W29: 258316.9 | X29: 362092.91 | Z29: 421618.58 | AA29: 476924.21 | AB29: 517417.63 | AC29: 659615.97 | AD29: 1.1222718
D30: 利益率 | E30: 0.22114753 | F30: 0.21808708 | G30: 0.25083167 | H30: 0.26880883 | I30: 0.26552075 | J30: 0.26304286 | K30: 0.27642611 | L30: 0.28048663 | M30: 0.26440014 | N30: 0.25701601 | O30: 0.26321874 | P30: 0.26298723 | R30: 0.19181883 | S30: 0.20520069 | T30: 0.19951775 | U30: 0.20317757 | W30: 0.20085601 | X30: 0.20439196 | Z30: 3.64395 | AA30: 3.7005901 | AB30: 0.2851252 | AC30: 3.2037974
A31: ｱﾙﾐﾅ基板 TOTAL | C31: 外部売上 | D31: 期初予算 | E31: 483343.02 | F31: 506279.1 | G31: 497007.37 | H31: 520531.62 | I31: 514603.67 | J31: 524026.53 | K31: 525588.47 | L31: 529321.78 | M31: 521301.92 | N31: 513293.44 | O31: 512257.96 | P31: 513607.89 | R31: 1486629.5 | S31: 1559161.8 | T31: 1576212.2 | U31: 1539159.3 | W31: 3045791.3 | X31: 3115371.4 | Z31: 0 | AA31: 4902827.7 | AB31: 5320199.4 | AC31: 6161162.7
D32: 実績値 | E32: 499841.72 | F32: 504945.39 | G32: 507247.43 | H32: 555489.46 | I32: 548441.69 | J32: 582096.89 | K32: 619845.7 | L32: 622891.62 | M32: 618108.07 | N32: 595324.8 | O32: 593133.23 | P32: 592948.2 | R32: 1512034.5 | S32: 1686028 | T32: 1860845.4 | U32: 1781406.2 | W32: 3198062.6 | X32: 3642251.6 | Z32: 4631571.9 | AA32: 5035461.3 | AB32: 5475876 | AC32: 6941289.1
C33: 営業利益 | D33: 期初予算 | E33: 74732.749 | F33: 89548.246 | G33: 75910.724 | H33: 103820.92 | I33: 100143.84 | J33: 100964.33 | K33: 106665.23 | L33: 109866.55 | M33: 101768.74 | N33: 104101.51 | O33: 103828.16 | P33: 103862.5 | R33: 240191.72 | S33: 304929.09 | T33: 318300.52 | U33: 311792.18 | W33: 545120.81 | X33: 630092.7 | Z33: 0 | AA33: 678120.03 | AB33: 980437.78 | AC33: 1175213.5
D34: 実績値 | E34: 75435.085 | F34: 78912.892 | G34: 85485.532 | H34: 99301.796 | I34: 101020.88 | J34: 100859.21 | K34: 128299.75 | L34: 126624.21 | M34: 124939.41 | N34: 118361.1 | O34: 116388.93 | P34: 121819.01 | R34: 239833.51 | S34: 301181.88 | T34: 379863.37 | U34: 356569.04 | W34: 541015.39 | X34: 736432.41 | Z34: 346742.97 | AA34: 790738.78 | AB34: 922011.09 | AC34: 1305469.4
D36: 予算 | E36: =+E33/E31 -> 0.15461638 | F36: =+F33/F31 -> 0.17687526 | G36: =+G33/G31 -> 0.15273561 | H36: =+H33/H31 -> 0.1994517 | I36: =+I33/I31 -> 0.19460382 | J36: =+J33/J31 -> 0.19267027 | K36: =+K33/K31 -> 0.20294438 | L36: =+L33/L31 -> 0.20756099 | ... X36: =+X33/X31 -> 0.20225283 | AB36: 0.18428591 | AC36: 0.19074541
D37: 実績値 | E37: =+E34/E32 -> 0.15091794 | F37: =+F34/F32 -> 0.15628005 | G37: =+G34/G32 -> 0.16852827 | H37: =+H34/H32 -> 0.1787645 | I37: =+I34/I32 -> 0.18419621 | J37: =+J34/J32 -> 0.17326877 | K37: =+K34/K32 -> 0.20698659 | L37: =+L34/L32 -> 0.20328449 | ... X37: =+X34/X32 -> 0.20219152 | AB37: 0.16837691 | AC37: -0.028441203
X39: 0.20684533
E40: 43191 | F40: 43221 | G40: 43252 | H40: 43282 | I40: 43313 | J40: 43344 | K40: 43374 | L40: 43405 | M40: 43435 | N40: 43466 | O40: 43497 | P40: 43525
A41: ﾊﾞﾙﾌﾞ | C41: 外部売上 | D41: 期初予算 | E41: 33836 | F41: 34523 | G41: 34509 | H41: 33803 | I41: 33824 | J41: 34011 | K41: 33449 | L41: 38592 | M41: 35024 | N41: 36422 | O41: 34571 | P41: 35419 | R41: 102868 | S41: 101638 | T41: 107065 | U41: 106412 | W41: 204506 | X41: 213477 | Z41: 0 | AA41: 444116 | AB41: 391744.75 | AC41: 417983
D42: 実績値 | E42: 40531.811 | F42: 42072.565 | G42: 40174.258 | H42: 43802.345 | I42: 41958.693 | J42: 41958.693 | K42: 37926.601 | L42: 38592 | M42: 35024 | N42: 36422 | O42: 34571 | P42: 35419 | R42: 122778.63 | S42: 127719.73 | T42: 111542.6 | U42: 106412 | W42: 250498.37 | X42: 217954.6 | Z42: 0 | AA42: 387831.74 | AB42: 417809.65 | AC42: 468452.97
C43: 営業利益 | D43: 期初予算 | E43: 4955.2 | F43: 5356.2 | G43: 5420.2 | H43: 5000.2 | I43: 5125.2 | J43: 5234.2 | K43: 4620.2 | L43: 7371.2 | M43: 6013.2 | N43: 6371.2 | O43: 5690.2 | P43: 6278.2 | R43: 15731.6 | S43: 15359.6 | T43: 18004.6 | U43: 18339.6 | W43: 31091.2 | X43: 36344.2 | Z43: 0 | AA43: 124286.03 | AB43: 83900.462 | AC43: 67435.4
D44: 実績値 | E44: 9484.6607 | F44: 9706.1359 | G44: 9413.1577 | H44: 10626.393 | I44: 8338.3771 | J44: 8415.3 | K44: 7255.7942 | L44: 7371.2 | M44: 6013.2 | N44: 6371.2 | O44: 5690.2 | P44: 6278.2 | R44: 28603.954 | S44: 27380.071 | T44: 20640.194 | U44: 18339.6 | W44: 55984.025 | X44: 38979.794 | Z44: 0 | AA44: 68238.313 | AB44: 79338.15 | AC44: 94963.819
D45: 利益率 | E45: 0.23400535 | F45: 0.23069988 | G45: 0.23430819 | H45: 0.24259873 | I45: 0.19872824 | J45: 0.20056154 | K45: 0.19131148 | L45: 0.19100332 | M45: 0.17168799 | N45: 0.17492724 | O45: 0.1645946 | P45: 0.17725515 | R45: 0.15292997 | S45: 0.15112064 | T45: 0.16816513 | U45: 0.17234522 | W45: 0.15203075 | X45: 0.17024879 | Z45: 0 | AA45: 2.1162942 | AB45: 0.21417125 | AC45: 2.4116817
A46: マグネット | C46: 外部売上 | D46: 期初予算 | E46: 30543.685 | F46: 31187.042 | G46: 30898.282 | H46: 28112.594 | I46: 28268.724 | J46: 28703.042 | K46: 29874.192 | L46: 30186.504 | M46: 30498.79 | N46: 28689.494 | O46: 28815.424 | P46: 28802.102 | R46: 92629.008 | S46: 85084.359 | T46: 90559.485 | U46: 86307.019 | W46: 177713.37 | X46: 176866.5 | Z46: 0 | AA46: 342509.56 | AB46: 352954.85 | AC46: 354579.87
D47: 実績値 | E47: 33269.303 | F47: 31767.709 | G47: 32903.127 | H47: 33950.042 | I47: 33796.848 | J47: 33796.848 | K47: 34547.995 | L47: 30186.504 | M47: 30498.79 | N47: 28689.494 | O47: 28815.424 | P47: 28802.102 | R47: 97940.139 | S47: 101543.74 | T47: 95233.288 | U47: 86307.019 | W47: 199483.88 | X47: 181540.31 | Z47: 0 | AA47: 355162.51 | AB47: 370206.06 | AC47: 381024.18
C48: 営業利益 | D48: 期初予算 | E48: -1284.01 | F48: -899.10256 | G48: -1032.8598 | H48: -1631.7194 | I48: -1776.9858 | J48: -1517.2667 | K48: -1380.8735 | L48: -1176.6973 | M48: -811.39322 | N48: -1381.9679 | O48: -1440.4325 | P48: -1285.851 | R48: -3215.9723 | S48: -4925.9719 | T48: -3368.964 | U48: -4108.2514 | W48: -8141.9442 | X48: -7477.2154 | Z48: 0 | AA48: 25893.313 | AB48: 11850.313 | AC48: -15619.16
D49: 実績値 | E49: 745.07009 | F49: 94.849646 | G49: 550.1431 | H49: 931.1512 | I49: 75.461817 | J49: 152.385 | K49: -118.41441 | L49: -1176.6973 | M49: -811.39322 | N49: -1381.9679 | O49: -1440.4325 | P49: -1285.851 | R49: 1390.0628 | S49: 1158.998 | T49: -2106.5049 | U49: -4108.2514 | W49: 2549.0609 | X49: -6214.7563 | Z49: 0 | AA49: 7389.1738 | AB49: -22604.826 | AC49: -3665.6955
D50: 利益率 | E50: 0.022395122 | F50: 0.0029857251 | G50: 0.016720086 | H50: 0.0274271 | I50: 0.0022328063 | J50: 0.0045088524 | K50: -0.0034275336 | L50: -0.038980906 | M50: -0.026604112 | N50: -0.048169825 | O50: -0.049988246 | P50: -0.044644347 | R50: -0.034718846 | S50: -0.057895152 | T50: -0.037201669 | U50: -0.047600432 | W50: -0.045815035 | X50: -0.04227604 | Z50: 0 | AA50: 0.23284745 | AB50: 0.033574586 | AC50: -0.13554528
A51: MALAYSIA TOTAL | C51: 外部売上 | D51: 期初予算 | E51: 547722.7 | F51: 571989.14 | G51: 562414.65 | H51: 582447.21 | I51: 576696.39 | J51: 586740.57 | K51: 588911.66 | L51: 598100.28 | M51: 586824.71 | N51: 578404.93 | O51: 575644.38 | P51: 577828.99 | R51: 1682126.5 | S51: 1745884.2 | T51: 1773836.6 | U51: 1731878.3 | W51: 3428010.7 | X51: 3505715 | Z51: 0 | AA51: 5631705 | AB51: 6064899 | AC51: 6933725.6
D52: 実績値 | E52: 573642.84 | F52: 578785.67 | G52: 580324.82 | H52: 633241.84 | I52: 624197.23 | J52: 657852.43 | K52: 692320.3 | L52: 691670.13 | M52: 683630.86 | N52: 660436.29 | O52: 656519.66 | P52: 657169.3 | R52: 1732753.3 | S52: 1915291.5 | T52: 2067621.3 | U52: 1974125.3 | W52: 3648044.8 | X52: 4041746.5 | Z52: 0 | AA52: 5778455.6 | AB52: 6263891.7 | AC52: 7790766.2
C53: 営業利益 | D53: 期初予算 | E53: 78403.939 | F53: 94005.343 | G53: 80298.064 | H53: 107189.4 | I53: 103492.06 | J53: 104681.27 | K53: 109904.55 | L53: 116061.06 | M53: 106970.55 | N53: 109090.74 | O53: 108077.93 | P53: 108854.85 | R53: 252707.35 | S53: 315362.72 | T53: 332936.16 | U53: 326023.52 | W53: 568070.07 | X53: 658959.68 | Z53: 0 | AA53: 855901.24 | AB53: 1076188.6 | AC53: 1227029.7 | AD53: 0.17744542
D54: 実績値 | E54: 85664.816 | F54: 88713.878 | G54: 95448.833 | H54: 110859.34 | I54: 109434.72 | J54: 109426.9 | K54: 135437.13 | L54: 132818.71 | M54: 130141.22 | N54: 123350.33 | O54: 120638.7 | P54: 126811.36 | R54: 269827.53 | S54: 329720.95 | T54: 398397.05 | U54: 370800.39 | W54: 599548.48 | X54: 769197.45 | Z54: 0 | AA54: 866366.27 | AB54: 978744.42 | AC54: 1396767.5
D55: 利益率 | E55: =+E54/E52 -> 0.14933476 | F55: =+F54/F52 -> 0.15327587 | G55: =+G54/G52 -> 0.16447484 | H55: =+H54/H52 -> 0.17506635 | I55: =+I54/I52 -> 0.17532073 | J55: =+J54/J52 -> 0.16633958 | K55: =+K54/K52 -> 0.19562785 | L55: =+L54/L52 -> 0.19202609 | ... P55: =+P54/P52 -> 0.19296604 | R55: =+R54/R52 -> 0.15572183 | S55: =+S54/S52 -> 0.17215184 | T55: =+T54/T52 -> 0.19268377 | U55: =+U54/U52 -> 0.18783023 | W55: =+W54/W52 -> 0.16434789 | X55: =+X54/X52 -> 0.19031313 | Z55: 0 | AA55: 1.7988351 | AB55: 0.17744542 | AC55: 0.17696543
C56: 予算
A57: FINANCE PROFIT | E57: 43191 | F57: 43221 | G57: 43252 | H57: 43282 | I57: 43313 | J57: 43344 | K57: 43374 | L57: 43405 | M57: 43435 | N57: 43466 | O57: 43497 | P57: 43525 | R57: 1Q | S57: 2Q | T57: 3Q | U57: 4Q | W57: 上期 | X57: 下期 | AB57: 2017 | AD57: 予算増減
A58: チップJM | C58: 外部売上 | D58: 期初予算 | E58: 0 | F58: 0 | G58: 0 | H58: 0 | I58: 0 | J58: 0 | K58: 0 | L58: 0 | M58: 0 | N58: 0 | O58: 0 | P58: 0 | R58: 0 | S58: 0 | T58: 0 | U58: 0 | W58: 0 | X58: 0 | AB58: 0
D59: 実績値 | E59: 0 | F59: 0 | G59: 0 | H59: 0 | I59: 0 | J59: 0 | K59: 0 | L59: 0 | M59: 0 | N59: 0 | O59: 0 | P59: 0 | R59: 0 | S59: 0 | T59: 0 | U59: 0 | W59: 0 | X59: 0 | AB59: 300.38
C60: 営業利益 | D60: 期初予算 | E60: 0 | F60: 0 | G60: 0 | H60: 0 | I60: 0 | J60: 0 | K60: 0 | L60: 0 | M60: 0 | N60: 0 | O60: 0 | P60: 0 | R60: 0 | S60: 0 | T60: 0 | U60: 0 | W60: 0 | X60: 0 | AB60: 0
D61: 実績値 | E61: 0 | F61: 0 | G61: 0 | H61: 0 | I61: 0 | J61: 0 | K61: 0 | L61: 0 | M61: 0 | N61: 0 | O61: 0 | P61: 0 | R61: 0 | S61: 0 | T61: 0 | U61: 0 | W61: 0 | X61: 0 | AB61: -955.147
A62: チップ商品+HIC | C62: 外部売上 | D62: 期初予算 | E62: 44927.775 | F62: 45091.975 | G62: 45782.775 | H62: 44991.975 | I62: 44542.055 | J62: 45511.975 | K62: 46689.18 | L62: 45686.975 | M62: 45037.055 | N62: 46476.975 | O62: 45602.055 | P62: 46476.975 | R62: 135802.52 | S62: 135046.01 | T62: 137413.21 | U62: 138556.01 | W62: 270848.53 | X62: 275969.21 | AB62: 475365.6
D63: 実績値 | E63: 52985.223 | F63: 43235.188 | G63: 53392.121 | H63: 56557.742 | I63: 44047.638 | J63: 45511.975 | K63: 46267.295 | L63: 46235.215 | M63: 52557.835 | N63: 49590.165 | O63: 52192.285 | P63: 52355.165 | R63: 149612.53 | S63: 146117.36 | T63: 145060.35 | U63: 154137.61 | W63: 295729.89 | X63: 299197.96 | AB63: 596657.66
C64: 営業利益 | D64: 期初予算 | E64: -8910.0642 | F64: -8901.8542 | G64: -8867.3142 | H64: -6875 | I64: -6875 | J64: -8880.8542 | K64: -8821.994 | L64: -8872.1042 | M64: -8904.6002 | N64: -8832.6042 | O64: -8876.3502 | P64: -8832.6042 | R64: -26679.233 | S64: -22630.854 | T64: -26598.698 | U64: -26541.559 | W64: -49310.087 | X64: -53140.257 | AB64: -54695.16
D65: 実績値 | E65: -7736.395 | F65: -9231.928 | G65: -5002.934 | H65: -7486.984 | I65: -6827.201 | J65: -6593 | K65: -6593 | L65: -6593 | M65: -6593 | N65: -6593 | O65: -6593 | P65: -6593 | R65: -21971.257 | S65: -20907.185 | T65: -19779 | U65: -19779 | W65: -42878.442 | X65: -39558 | AB65: -82105.129
A66: チップMM | C66: 外部売上 | D66: 期初予算 | E66: 305888.85 | F66: 307110.85 | G66: 304786.85 | H66: 324635.61 | I66: 326192.26 | J66: 323863.26 | K66: 326529.76 | L66: 332113.26 | M66: 330927.76 | N66: 315725.78 | O66: 319343.15 | P66: 318131.77 | R66: 917786.55 | S66: 974691.13 | T66: 989570.78 | U66: 953200.7 | W66: 1892477.7 | X66: 1942771.5 | AB66: 3236670.3
D67: 実績値 | E67: 293300.39 | F67: 305618.27 | G67: 289163.18 | H67: 323741.68 | I67: 334377.78 | J67: 327885.28 | K67: 340579.85 | L67: 341994.92 | M67: 339171.84 | N67: 331484.81 | O67: 324257.35 | P67: 323511.23 | R67: 888081.84 | S67: 986004.74 | T67: 1021746.6 | U67: 979253.38 | W67: 1874086.6 | X67: 2001000 | AB67: 2952301.3
C68: 内部売上 | D68: 期初予算 | E68: 41319.352 | F68: 41014.592 | G68: 41319.352 | H68: 40919.592 | I68: 41414.352 | J68: 41413.592 | K68: 42577.271 | L68: 41082.992 | M68: 41387.752 | N68: 41025.992 | O68: 41520.752 | P68: 41025.992 | R68: 123653.3 | S68: 123747.54 | T68: 125048.02 | U68: 123572.74 | AB68: 368458.19
D69: 実績値 | E69: 45454.656 | F69: 46776.6 | G69: 40247.625 | H69: 36475.063 | I69: 41938.799 | J69: 41413.592 | K69: 42013.194 | L69: 42362.718 | M69: 48576.478 | N69: 45202.696 | O69: 48229.206 | P69: 47829.446 | R69: 132478.88 | S69: 119827.45 | T69: 132952.39 | U69: 141261.35 | W69: 252306.33 | AB69: 512705.14
C70: 営業利益 | D70: 期初予算 | E70: 61743.929 | F70: 65333.251 | G70: 55700.489 | H70: 78838.731 | I70: 79108.432 | J70: 76457.649 | K70: 84484.595 | L70: 86544.26 | M70: 83145.116 | N70: 80952.156 | O70: 82695.113 | P70: 82147.605 | R70: 182777.67 | S70: 234404.81 | T70: 254173.97 | U70: 245794.87 | W70: 417182.48 | X70: 499968.85 | AB70: 574088.07
D71: 実績値 | E71: 52512.663 | F71: 50474.204 | G71: 48601.083 | H71: 71795.279 | I71: 58797.406 | J71: 54570.92 | K71: 69436.89 | L71: 64941.27 | M71: 64161.01 | N71: 70876.27 | O71: 68428.12 | P71: 69690.67 | R71: 151587.95 | S71: 185163.61 | T71: 198539.17 | U71: 208995.06 | W71: 336751.56 | X71: 407534.23 | AB71: 460150.67
A72: チップ連結 | C72: 外部売上 | D72: 期初予算 | E72: 350816.63 | F72: 352202.83 | G72: 350569.63 | H72: 369627.59 | I72: 370734.32 | J72: 369375.24 | K72: 373218.94 | L72: 377800.24 | M72: 375964.82 | N72: 362202.76 | O72: 364945.2 | P72: 364608.75 | R72: 1053589.1 | S72: 1109737.1 | T72: 1126984 | U72: 1091756.7 | W72: 2163326.2 | X72: 2218740.7 | AB72: 3712035.9
D73: 実績値 | E73: 346285.61 | F73: 348853.45 | G73: 342555.3 | H73: 380299.43 | I73: 378425.42 | J73: 373397.25 | K73: 386847.15 | L73: 388230.13 | M73: 391729.68 | N73: 381074.97 | O73: 376449.63 | P73: 375866.4 | R73: 1037694.4 | S73: 1132122.1 | T73: 1166807 | U73: 1133391 | W73: 2169816.5 | X73: 2300198 | AB73: 3549259.3
C74: 営業利益 | D74: 期初予算 | E74: 52833.864 | F74: 56431.397 | G74: 46833.175 | H74: 71963.731 | I74: 72233.432 | J74: 67576.795 | K74: 75662.601 | L74: 77672.156 | M74: 74240.516 | N74: 72119.552 | O74: 73818.763 | P74: 73315.001 | R74: 156098.44 | S74: 211773.96 | T74: 227575.27 | U74: 219253.32 | W74: 367872.39 | X74: 446828.59 | AB74: 519392.91
D75: 実績値 | E75: 44776.268 | F75: 41242.276 | G75: 43598.149 | H75: 64308.295 | I75: 51970.205 | J75: 47977.92 | K75: 62843.89 | L75: 58348.27 | M75: 57568.01 | N75: 64283.27 | O75: 61835.12 | P75: 63097.67 | R75: 129616.69 | S75: 164256.42 | T75: 178760.17 | U75: 189216.06 | W75: 293873.11 | X75: 367976.23 | AB75: 377090.4
D76: 利益率 | E76: 0.12930444 | F76: 0.11822235 | G76: 0.12727332 | H76: 0.13662909 | I76: 0.14561733 | J76: 0.12180805 | K76: 0.16370331 | L76: 0.15543356 | M76: 0.16518595 | N76: 0.1647426 | O76: 0.156671 | P76: 0.17080827 | R76: 0.14815875 | S76: 0.19083254 | T76: 0.20193301 | U76: 0.20082617 | W76: 0.17004943 | X76: 0.20138838 | AB76: 0.1399213
A77: 大型基板MM | C77: 外部売上 | D77: 期初予算 | E77: 132526.39 | F77: 154076.27 | G77: 146437.74 | H77: 150904.03 | I77: 143869.36 | J77: 154651.29 | K77: 152369.53 | L77: 151521.54 | M77: 145337.11 | N77: 151090.68 | O77: 147312.76 | P77: 148999.14 | R77: 433040.4 | S77: 449424.68 | T77: 449228.17 | U77: 447402.58 | W77: 882465.08 | X77: 896630.75 | AB77: 1608163.4
D78: 実績値 | E78: 153556.11 | F78: 156091.94 | G78: 164692.13 | H78: 175190.03 | I78: 170016.27 | J78: 208699.64 | K78: 232998.55 | L78: 234661.49 | M78: 226378.39 | N78: 214249.83 | O78: 216683.6 | P78: 217081.81 | R78: 474340.18 | S78: 553905.94 | T78: 694038.44 | U78: 648015.23 | W78: 1028246.1 | X78: 1342053.7 | AB78: 1926616.7
C79: 内部売上 | D79: 期初予算 | E79: 1362.034 | F79: 1822.784 | G79: 2174.284 | H79: 1822.784 | I79: 900.6 | J79: 1822.784 | K79: 1777.45 | L79: 2319.634 | M79: 1397.45 | N79: 3127.134 | O79: 1801.2 | P79: 3127.134 | R79: 5359.102 | S79: 4546.168 | T79: 5494.534 | U79: 8055.468 | AB79: 8827.573
D80: 実績値 | E80: 487.85739 | F80: 1040.325 | G80: 151.93778 | H80: 927.061 | I80: 2910.253 | J80: 1822.784 | K80: 2042.88 | L80: 1642.88 | M80: 1424.7 | N80: 2008.38 | O80: 1424.7 | P80: 2008.38 | R80: 1680.1202 | S80: 5660.098 | T80: 5110.46 | U80: 5441.46 | W80: 7340.2182 | AB80: 13073.06
C81: 営業利益 | D81: 期初予算 | E81: 21898.885 | F81: 33116.849 | G81: 29077.549 | H81: 31857.185 | I81: 27910.409 | J81: 33387.539 | K81: 31002.626 | L81: 32194.398 | M81: 27528.228 | N81: 31981.959 | O81: 30009.397 | P81: 30547.504 | R81: 84093.282 | S81: 93155.133 | T81: 90725.251 | U81: 92538.861 | W81: 177248.41 | X81: 183264.11 | AB81: 461044.87
D82: 実績値 | E82: 44855.944 | F82: 40652.41 | G82: 41353.202 | H82: 45589.478 | I82: 57510.859 | J82: 54222.771 | K82: 67404.68 | L82: 68738.545 | M82: 62152.897 | N82: 56420.699 | O82: 59387.733 | P82: 59942.948 | Q82: 69317.386 | R82: 126861.56 | S82: 157323.11 | T82: 198296.12 | U82: 175751.38 | W82: 284184.66 | X82: 374047.5 | AB82: 473173.03
D83: 利益率 | E83: 0.29118922 | F83: 0.25871459 | G83: 0.25086255 | H83: 0.26880883 | I83: 0.26552075 | J83: 0.26304286 | K83: 0.27642611 | L83: 0.28048663 | M83: 0.26440014 | N83: 0.25701601 | O83: 0.26321874 | P83: 0.26298723 | R83: 0.19181883 | S83: 0.20520069 | T83: 0.19951775 | U83: 0.20317757 | W83: 0.20085601 | X83: 0.20439196 | AB83: 0.2851252
A84: ｱﾙﾐﾅ基板 TOTAL | C84: 外部売上 | D84: 期初予算 | E84: 483343.02 | F84: 506279.1 | G84: 497007.37 | H84: 520531.62 | I84: 514603.67 | J84: 524026.53 | K84: 525588.47 | L84: 529321.78 | M84: 521301.92 | N84: 513293.44 | O84: 512257.96 | P84: 513607.89 | R84: 1486629.5 | S84: 1559161.8 | T84: 1576212.2 | U84: 1539159.3 | W84: 3045791.3 | X84: 3115371.4 | AB84: 5320199.4
D85: 実績値 | E85: 499841.72 | F85: 504945.39 | G85: 507247.43 | H85: 555489.46 | I85: 548441.69 | J85: 582096.89 | K85: 619845.7 | L85: 622891.62 | M85: 618108.07 | N85: 595324.8 | O85: 593133.23 | P85: 592948.2 | R85: 1512034.5 | S85: 1686028 | T85: 1860845.4 | U85: 1781406.2 | W85: 3198062.6 | X85: 3642251.6 | AB85: 5475876
C86: 営業利益 | D86: 期初予算 | E86: 74732.749 | F86: 89548.246 | G86: 75910.724 | H86: 103820.92 | I86: 100143.84 | J86: 100964.33 | K86: 106665.23 | L86: 109866.55 | M86: 101768.74 | N86: 104101.51 | O86: 103828.16 | P86: 103862.5 | R86: 240191.72 | S86: 304929.09 | T86: 318300.52 | U86: 311792.18 | W86: 545120.81 | X86: 630092.7 | AB86: 980437.78
D87: 実績値 | E87: 89632.212 | F87: 81894.686 | G87: 84951.351 | H87: 109897.77 | I87: 109481.06 | J87: 102200.69 | K87: 130248.57 | L87: 127086.81 | M87: 119720.91 | N87: 120703.97 | O87: 121222.85 | P87: 123040.62 | R87: 256478.25 | S87: 321579.53 | T87: 377056.29 | U87: 364967.44 | W87: 578057.78 | X87: 742023.73 | AB87: 850263.43
D89: 予算 | E89: =+E86/E84 -> 0.15461638 | F89: =+F86/F84 -> 0.17687526 | G89: =+G86/G84 -> 0.15273561 | H89: =+H86/H84 -> 0.1994517 | I89: =+I86/I84 -> 0.19460382 | J89: =+J86/J84 -> 0.19267027 | K89: =+K86/K84 -> 0.20294438 | L89: =+L86/L84 -> 0.20756099 | ... P89: =+P86/P84 -> 0.2022214 | R89: =+R86/R84 -> 0.16156798 | S89: =+S86/S84 -> 0.19557245 | T89: =+T86/T84 -> 0.20194015 | U89: =+U86/U84 -> 0.20257304 | W89: =+W86/W84 -> 0.1789751 | X89: =+X86/X84 -> 0.20225283 | AB89: 0.18428591 | AC89: #DIV/0!
D90: 実績値 | E90: =+E87/E85 -> 0.17932119 | F90: =+F87/F85 -> 0.16218523 | G90: =+G87/G85 -> 0.16747517 | H90: =+H87/H85 -> 0.19783953 | I90: =+I87/I85 -> 0.19962207 | J90: =+J87/J85 -> 0.17557333 | K90: =+K87/K85 -> 0.21013063 | L90: =+L87/L85 -> 0.20402717 | ... P90: =+P87/P85 -> 0.20750652 | R90: =+R87/R85 -> 0.1696246 | S90: =+S87/S85 -> 0.19073202 | T90: =+T87/T85 -> 0.20262634 | U90: =+U87/U85 -> 0.20487603 | W90: =+W87/W85 -> 0.18075249 | X90: =+X87/X85 -> 0.20372665 | AB90: 0.15527441 | AC90: -0.028441203
X92: 0.20366528
E93: 43191 | F93: 43221 | G93: 43252 | H93: 43282 | I93: 43313 | J93: 43344 | K93: 43374 | L93: 43405 | M93: 43435 | N93: 43466 | O93: 43497 | P93: 43525
A94: ﾊﾞﾙﾌﾞ | C94: 外部売上 | D94: 期初予算 | E94: 33836 | F94: 34523 | G94: 34509 | H94: 33803 | I94: 33824 | J94: 34011 | K94: 33449 | L94: 38592 | M94: 35024 | N94: 36422 | O94: 34571 | P94: 35419 | R94: 102868 | S94: 101638 | T94: 107065 | U94: 106412 | W94: 204506 | X94: 213477 | AB94: 391744.75
D95: 実績値 | E95: 40531.811 | F95: 42072.565 | G95: 40174.258 | H95: 43802.345 | I95: 41958.693 | J95: 41958.693 | K95: 37926.601 | L95: 38592 | M95: 35024 | N95: 36422 | O95: 34571 | P95: 35419 | R95: 122778.63 | S95: 127719.73 | T95: 111542.6 | U95: 106412 | W95: 250498.37 | X95: 217954.6 | AB95: 417809.65
C96: 営業利益 | D96: 期初予算 | E96: 4955.2 | F96: 5356.2 | G96: 5420.2 | H96: 5000.2 | I96: 5125.2 | J96: 5234.2 | K96: 4620.2 | L96: 7371.2 | M96: 6013.2 | N96: 6371.2 | O96: 5690.2 | P96: 6278.2 | R96: 15731.6 | S96: 15359.6 | T96: 18004.6 | U96: 18339.6 | W96: 31091.2 | X96: 36344.2 | AB96: 83900.462 | AC96: 0
D97: 実績値 | E97: 9874.9907 | F97: 9687.2204 | G97: 7938.1785 | H97: 10514.304 | I97: 7334.6533 | J97: 7411.576 | K97: 7257.7906 | L97: 7371.2 | M97: 6013.2 | N97: 6371.2 | O97: 5690.2 | P97: 6278.2 | R97: 27500.39 | S97: 25260.533 | T97: 20642.191 | U97: 18339.6 | W97: 52760.922 | X97: 38981.791 | AB97: 78034.889
D98: 利益率 | E98: 0.24363556 | F98: 0.23025029 | G98: 0.19759366 | H98: 0.24259873 | I98: 0.19872824 | J98: 0.20056154 | K98: 0.19131148 | L98: 0.19100332 | M98: 0.17168799 | N98: 0.17492724 | O98: 0.1645946 | P98: 0.17725515 | R98: 0.15292997 | S98: 0.15112064 | T98: 0.16816513 | U98: 0.17234522 | W98: 0.15203075 | X98: 0.17024879 | AB98: 0.21417125
A99: マグネット | C99: 外部売上 | D99: 期初予算 | E99: 30543.685 | F99: 31187.042 | G99: 30898.282 | H99: 28112.594 | I99: 28268.724 | J99: 28703.042 | K99: 29874.192 | L99: 30186.504 | M99: 30498.79 | N99: 28689.494 | O99: 28815.424 | P99: 28802.102 | R99: 92629.008 | S99: 85084.359 | T99: 90559.485 | U99: 86307.019 | W99: 177713.37 | X99: 176866.5 | AB99: 352954.85
D100: 実績値 | E100: 33269.303 | F100: 31767.709 | G100: 32903.127 | H100: 33950.042 | I100: 33796.848 | J100: 33796.848 | K100: 34547.995 | L100: 30186.504 | M100: 30498.79 | N100: 28689.494 | O100: 28815.424 | P100: 28802.102 | R100: 97940.139 | S100: 101543.74 | T100: 95233.288 | U100: 86307.019 | W100: 199483.88 | X100: 181540.31 | AB100: 370206.06
C101: 営業利益 | D101: 期初予算 | E101: -1284.01 | F101: -899.10256 | G101: -1032.8598 | H101: -1631.7194 | I101: -1776.9858 | J101: -1517.2667 | K101: -1380.8735 | L101: -1176.6973 | M101: -811.39322 | N101: -1381.9679 | O101: -1440.4325 | P101: -1285.851 | R101: -3215.9723 | S101: -4925.9719 | T101: -3368.964 | U101: -4108.2514 | W101: -8141.9442 | X101: -7477.2154 | AB101: 11850.313
D102: 実績値 | E102: 1135.9022 | F102: 1048.4137 | G102: 91.874821 | H102: 713.5438 | I102: -71.287068 | J102: 5.636 | K102: -115.18307 | L102: -1176.6973 | M102: -811.39322 | N102: -1381.9679 | O102: -1440.4325 | P102: -1285.851 | R102: 2276.1907 | S102: 647.89273 | T102: -2103.2736 | U102: -4108.2514 | W102: 2924.0835 | X102: -6211.525 | AB102: -18474.749
D103: 利益率 | E103: 0.034142651 | F103: 0.033002497 | G103: 0.0027922823 | H103: 0.0274271 | I103: 0.0022328063 | J103: 0.0045088524 | K103: -0.0034275336 | L103: -0.038980906 | M103: -0.026604112 | N103: -0.048169825 | O103: -0.049988246 | P103: -0.044644347 | R103: -0.034718846 | S103: -0.057895152 | T103: -0.037201669 | U103: -0.047600432 | W103: -0.045815035 | X103: -0.04227604 | AB103: 0.033574586
A104: MALAYSIA TOTAL | C104: 外部売上 | D104: 期初予算 | E104: 547722.7 | F104: 571989.14 | G104: 562414.65 | H104: 582447.21 | I104: 576696.39 | J104: 586740.57 | K104: 588911.66 | L104: 598100.28 | M104: 586824.71 | N104: 578404.93 | O104: 575644.38 | P104: 577828.99 | R104: 1682126.5 | S104: 1745884.2 | T104: 1773836.6 | U104: 1731878.3 | W104: 3428010.7 | X104: 3505715 | AB104: 6064899
...

Sheet Sheet3

Sheet Sheet1
